Workbook
Name TaxYear: Setup!$C$6
Name MileRate: Setup!$C$7
Name VehicleList: Setup!$B$12:$B$14
Name PlatformList: Setup!$B$19:$B$30

Sheet Start Here
B2: Gig Driver Mileage Tracker 2026
B3: SideHustleGuard · sidehustleguard.com
B6: What this tracker does
B7: Logs every business trip you take for DoorDash, Uber, Lyft, Grubhub, Instacart, Amazon Flex, TaskRabbit, Rover, or any other gig platform. Auto-calculates your IRS standard mileage deduction — the single biggest tax break gig workers get, typically worth $5,000–$15,000+ off your taxable income each year.
B9: How to use it (3 steps)
B10: 1. | C10: Open the Setup tab. | D10: Set the tax year, confirm the IRS mileage rate (we pre-fill it; verify at IRS.gov each January), and list your vehicles + the platforms you drive for.
B11: 2. | C11: Log trips on the Trip Log tab. | D11: One row per trip. Pick the date, vehicle, and platform from dropdowns. Enter miles directly OR enter your start and end odometer — whichever is faster. Default business % is 100 because most gig trips are 100% business.
B12: 3. | C12: Check the Monthly & Year-End Summary tabs. | D12: Everything totals automatically. The Year-End Summary tells you exactly what to write on Schedule C line 9 (Car & Truck Expenses).
B14: What the IRS actually requires
B15: ✓ | C15: A contemporaneous log — entries made at or near the time of the trip, not reconstructed at year-end
B16: ✓ | C16: Date of each business trip
B17: ✓ | C17: Business purpose (e.g., "DoorDash delivery," "Uber pickup → drop-off")
B18: ✓ | C18: Total miles driven for that trip (or start + end odometer)
B19: ✓ | C19: Total miles driven for the year, including personal — this is the denominator that proves your business %
B21: This tracker captures all of the above. Save the file (or a print/PDF export) with your tax records for at least 3 years after filing — that's the standard IRS audit lookback window.
B23: Educational tool only — not tax or legal advice. The IRS standard mileage rate is set annually; verify the current year's rate at irs.gov/standardmileagerates before filing. For complex situations (employer reimbursements, multiple businesses, leased vehicles), consult a CPA.

Sheet Setup
B2: Setup
B3: Edit the gold cells below. The rest of the tracker reads from here.
B5: Tax year & rate
B6: Tax year | C6: 2026
B7: IRS standard mileage rate ($/mile) | C7: 0.7
B8: ← Verify at irs.gov/standardmileagerates each January. The IRS publishes the rate for the calendar year in mid-December.
B10: Your vehicles
B11: Vehicle name | C11: Year / Make / Model | D11: Starting odometer (Jan 1) | E11: Ending odometer (Dec 31) | F11: Total miles (year)
B12: Main car | C12: 2020 Toyota Corolla | D12: 38500 | E12: 78500 | F12: =IF(AND(ISNUMBER(D12),ISNUMBER(E12)),E12-D12,"")
B13: Second car | F13: =IF(AND(ISNUMBER(D13),ISNUMBER(E13)),E13-D13,"")
B14: Backup / rental | F14: =IF(AND(ISNUMBER(D14),ISNUMBER(E14)),E14-D14,"")
B16: Your gig platforms
B17: Edit this list to match the apps you actually drive for.
B18: Platform
B19: DoorDash
B20: Uber
B21: Uber Eats
B22: Lyft
B23: Grubhub
B24: Instacart
B25: Amazon Flex
B26: TaskRabbit
B27: Rover
... B30: Other

Sheet Trip Log
A1: Trip Log — one row per business trip. Use dropdowns where they appear.
A2: Date | B2: Vehicle | C2: Platform | D2: Purpose / Route | E2: Start odom. | F2: End odom. | G2: Miles | H2: Business % | I2: Business miles | J2: Deduction $ | K2: Notes
A3: 2026-01-03 | B3: Main car | C3: DoorDash | D3: Long Beach lunch shift | E3: 38500 | F3: 38582 | G3: =IF(AND(ISNUMBER(E3),ISNUMBER(F3)),F3-E3,"") | H3: 1 | I3: =IF(AND(ISNUMBER(G3),ISNUMBER(H3)),G3*H3,"") | J3: =IF(ISNUMBER(I3),I3*MileRate,"") | K3: First day driving — see formulas below for how miles/deduction auto-fill
A4: 2026-01-04 | B4: Main car | C4: Uber | D4: Friday airport runs | G4: 73 | H4: 1 | I4: =IF(AND(ISNUMBER(G4),ISNUMBER(H4)),G4*H4,"") | J4: =IF(ISNUMBER(I4),I4*MileRate,"") | K4: Used miles directly instead of odometer — both work
G5: =IF(AND(ISNUMBER(E5),ISNUMBER(F5)),F5-E5,"") | H5: 1 | I5: =IF(AND(ISNUMBER(G5),ISNUMBER(H5)),G5*H5,"") | J5: =IF(ISNUMBER(I5),I5*MileRate,"")
G6: =IF(AND(ISNUMBER(E6),ISNUMBER(F6)),F6-E6,"") | H6: 1 | I6: =IF(AND(ISNUMBER(G6),ISNUMBER(H6)),G6*H6,"") | J6: =IF(ISNUMBER(I6),I6*MileRate,"")
G7: =IF(AND(ISNUMBER(E7),ISNUMBER(F7)),F7-E7,"") | H7: 1 | I7: =IF(AND(ISNUMBER(G7),ISNUMBER(H7)),G7*H7,"") | J7: =IF(ISNUMBER(I7),I7*MileRate,"")
G8: =IF(AND(ISNUMBER(E8),ISNUMBER(F8)),F8-E8,"") | H8: 1 | I8: =IF(AND(ISNUMBER(G8),ISNUMBER(H8)),G8*H8,"") | J8: =IF(ISNUMBER(I8),I8*MileRate,"")
G9: =IF(AND(ISNUMBER(E9),ISNUMBER(F9)),F9-E9,"") | H9: 1 | I9: =IF(AND(ISNUMBER(G9),ISNUMBER(H9)),G9*H9,"") | J9: =IF(ISNUMBER(I9),I9*MileRate,"")
G10: =IF(AND(ISNUMBER(E10),ISNUMBER(F10)),F10-E10,"") | H10: 1 | I10: =IF(AND(ISNUMBER(G10),ISNUMBER(H10)),G10*H10,"") | J10: =IF(ISNUMBER(I10),I10*MileRate,"")
G11: =IF(AND(ISNUMBER(E11),ISNUMBER(F11)),F11-E11,"") | H11: 1 | I11: =IF(AND(ISNUMBER(G11),ISNUMBER(H11)),G11*H11,"") | J11: =IF(ISNUMBER(I11),I11*MileRate,"")
G12: =IF(AND(ISNUMBER(E12),ISNUMBER(F12)),F12-E12,"") | H12: 1 | I12: =IF(AND(ISNUMBER(G12),ISNUMBER(H12)),G12*H12,"") | J12: =IF(ISNUMBER(I12),I12*MileRate,"")
G13: =IF(AND(ISNUMBER(E13),ISNUMBER(F13)),F13-E13,"") | H13: 1 | I13: =IF(AND(ISNUMBER(G13),ISNUMBER(H13)),G13*H13,"") | J13: =IF(ISNUMBER(I13),I13*MileRate,"")
G14: =IF(AND(ISNUMBER(E14),ISNUMBER(F14)),F14-E14,"") | H14: 1 | I14: =IF(AND(ISNUMBER(G14),ISNUMBER(H14)),G14*H14,"") | J14: =IF(ISNUMBER(I14),I14*MileRate,"")
G15: =IF(AND(ISNUMBER(E15),ISNUMBER(F15)),F15-E15,"") | H15: 1 | I15: =IF(AND(ISNUMBER(G15),ISNUMBER(H15)),G15*H15,"") | J15: =IF(ISNUMBER(I15),I15*MileRate,"")
G16: =IF(AND(ISNUMBER(E16),ISNUMBER(F16)),F16-E16,"") | H16: 1 | I16: =IF(AND(ISNUMBER(G16),ISNUMBER(H16)),G16*H16,"") | J16: =IF(ISNUMBER(I16),I16*MileRate,"")
... G369: =IF(AND(ISNUMBER(E369),ISNUMBER(F369)),F369-E369,"") | H369: 1 | I369: =IF(AND(ISNUMBER(G369),ISNUMBER(H369)),G369*H369,"") | J369: =IF(ISNUMBER(I369),I369*MileRate,"")

Sheet Monthly Summary
B2: Monthly Summary
B3: Pulled from the Trip Log automatically. Edit nothing here.
B5: Month | C5: Trips | D5: Total miles | E5: Business miles | F5: Deduction $
B6: January | C6: =SUMPRODUCT((MONTH('Trip Log'!$A$3:$A$369)=1)*(YEAR('Trip Log'!$A$3:$A$369)=TaxYear)*ISNUMBER('Trip Log'!$G$3:$G$369)) | D6: =SUMPRODUCT((MONTH('Trip Log'!$A$3:$A$369)=1)*(YEAR('Trip Log'!$A$3:$A$369)=TaxYear)*IFERROR('Trip Log'!$G$3:$G$369,0)) | E6: =SUMPRODUCT((MONTH('Trip Log'!$A$3:$A$369)=1)*(YEAR('Trip Log'!$A$3:$A$369)=TaxYear)*IFERROR('Trip Log'!$I$3:$I$369,0)) | F6: =SUMPRODUCT((MONTH('Trip Log'!$A$3:$A$369)=1)*(YEAR('Trip Log'!$A$3:$A$369)=TaxYear)*IFERROR('Trip Log'!$J$3:$J$369,0))
B7: February | C7: =SUMPRODUCT((MONTH('Trip Log'!$A$3:$A$369)=2)*(YEAR('Trip Log'!$A$3:$A$369)=TaxYear)*ISNUMBER('Trip Log'!$G$3:$G$369)) | D7: =SUMPRODUCT((MONTH('Trip Log'!$A$3:$A$369)=2)*(YEAR('Trip Log'!$A$3:$A$369)=TaxYear)*IFERROR('Trip Log'!$G$3:$G$369,0)) | E7: =SUMPRODUCT((MONTH('Trip Log'!$A$3:$A$369)=2)*(YEAR('Trip Log'!$A$3:$A$369)=TaxYear)*IFERROR('Trip Log'!$I$3:$I$369,0)) | F7: =SUMPRODUCT((MONTH('Trip Log'!$A$3:$A$369)=2)*(YEAR('Trip Log'!$A$3:$A$369)=TaxYear)*IFERROR('Trip Log'!$J$3:$J$369,0))
B8: March | C8: =SUMPRODUCT((MONTH('Trip Log'!$A$3:$A$369)=3)*(YEAR('Trip Log'!$A$3:$A$369)=TaxYear)*ISNUMBER('Trip Log'!$G$3:$G$369)) | D8: =SUMPRODUCT((MONTH('Trip Log'!$A$3:$A$369)=3)*(YEAR('Trip Log'!$A$3:$A$369)=TaxYear)*IFERROR('Trip Log'!$G$3:$G$369,0)) | E8: =SUMPRODUCT((MONTH('Trip Log'!$A$3:$A$369)=3)*(YEAR('Trip Log'!$A$3:$A$369)=TaxYear)*IFERROR('Trip Log'!$I$3:$I$369,0)) | F8: =SUMPRODUCT((MONTH('Trip Log'!$A$3:$A$369)=3)*(YEAR('Trip Log'!$A$3:$A$369)=TaxYear)*IFERROR('Trip Log'!$J$3:$J$369,0))
B9: April | C9: =SUMPRODUCT((MONTH('Trip Log'!$A$3:$A$369)=4)*(YEAR('Trip Log'!$A$3:$A$369)=TaxYear)*ISNUMBER('Trip Log'!$G$3:$G$369)) | D9: =SUMPRODUCT((MONTH('Trip Log'!$A$3:$A$369)=4)*(YEAR('Trip Log'!$A$3:$A$369)=TaxYear)*IFERROR('Trip Log'!$G$3:$G$369,0)) | E9: =SUMPRODUCT((MONTH('Trip Log'!$A$3:$A$369)=4)*(YEAR('Trip Log'!$A$3:$A$369)=TaxYear)*IFERROR('Trip Log'!$I$3:$I$369,0)) | F9: =SUMPRODUCT((MONTH('Trip Log'!$A$3:$A$369)=4)*(YEAR('Trip Log'!$A$3:$A$369)=TaxYear)*IFERROR('Trip Log'!$J$3:$J$369,0))
B10: May | C10: =SUMPRODUCT((MONTH('Trip Log'!$A$3:$A$369)=5)*(YEAR('Trip Log'!$A$3:$A$369)=TaxYear)*ISNUMBER('Trip Log'!$G$3:$G$369)) | D10: =SUMPRODUCT((MONTH('Trip Log'!$A$3:$A$369)=5)*(YEAR('Trip Log'!$A$3:$A$369)=TaxYear)*IFERROR('Trip Log'!$G$3:$G$369,0)) | E10: =SUMPRODUCT((MONTH('Trip Log'!$A$3:$A$369)=5)*(YEAR('Trip Log'!$A$3:$A$369)=TaxYear)*IFERROR('Trip Log'!$I$3:$I$369,0)) | F10: =SUMPRODUCT((MONTH('Trip Log'!$A$3:$A$369)=5)*(YEAR('Trip Log'!$A$3:$A$369)=TaxYear)*IFERROR('Trip Log'!$J$3:$J$369,0))
B11: June | C11: =SUMPRODUCT((MONTH('Trip Log'!$A$3:$A$369)=6)*(YEAR('Trip Log'!$A$3:$A$369)=TaxYear)*ISNUMBER('Trip Log'!$G$3:$G$369)) | D11: =SUMPRODUCT((MONTH('Trip Log'!$A$3:$A$369)=6)*(YEAR('Trip Log'!$A$3:$A$369)=TaxYear)*IFERROR('Trip Log'!$G$3:$G$369,0)) | E11: =SUMPRODUCT((MONTH('Trip Log'!$A$3:$A$369)=6)*(YEAR('Trip Log'!$A$3:$A$369)=TaxYear)*IFERROR('Trip Log'!$I$3:$I$369,0)) | F11: =SUMPRODUCT((MONTH('Trip Log'!$A$3:$A$369)=6)*(YEAR('Trip Log'!$A$3:$A$369)=TaxYear)*IFERROR('Trip Log'!$J$3:$J$369,0))
B12: July | C12: =SUMPRODUCT((MONTH('Trip Log'!$A$3:$A$369)=7)*(YEAR('Trip Log'!$A$3:$A$369)=TaxYear)*ISNUMBER('Trip Log'!$G$3:$G$369)) | D12: =SUMPRODUCT((MONTH('Trip Log'!$A$3:$A$369)=7)*(YEAR('Trip Log'!$A$3:$A$369)=TaxYear)*IFERROR('Trip Log'!$G$3:$G$369,0)) | E12: =SUMPRODUCT((MONTH('Trip Log'!$A$3:$A$369)=7)*(YEAR('Trip Log'!$A$3:$A$369)=TaxYear)*IFERROR('Trip Log'!$I$3:$I$369,0)) | F12: =SUMPRODUCT((MONTH('Trip Log'!$A$3:$A$369)=7)*(YEAR('Trip Log'!$A$3:$A$369)=TaxYear)*IFERROR('Trip Log'!$J$3:$J$369,0))
B13: August | C13: =SUMPRODUCT((MONTH('Trip Log'!$A$3:$A$369)=8)*(YEAR('Trip Log'!$A$3:$A$369)=TaxYear)*ISNUMBER('Trip Log'!$G$3:$G$369)) | D13: =SUMPRODUCT((MONTH('Trip Log'!$A$3:$A$369)=8)*(YEAR('Trip Log'!$A$3:$A$369)=TaxYear)*IFERROR('Trip Log'!$G$3:$G$369,0)) | E13: =SUMPRODUCT((MONTH('Trip Log'!$A$3:$A$369)=8)*(YEAR('Trip Log'!$A$3:$A$369)=TaxYear)*IFERROR('Trip Log'!$I$3:$I$369,0)) | F13: =SUMPRODUCT((MONTH('Trip Log'!$A$3:$A$369)=8)*(YEAR('Trip Log'!$A$3:$A$369)=TaxYear)*IFERROR('Trip Log'!$J$3:$J$369,0))
B14: September | C14: =SUMPRODUCT((MONTH('Trip Log'!$A$3:$A$369)=9)*(YEAR('Trip Log'!$A$3:$A$369)=TaxYear)*ISNUMBER('Trip Log'!$G$3:$G$369)) | D14: =SUMPRODUCT((MONTH('Trip Log'!$A$3:$A$369)=9)*(YEAR('Trip Log'!$A$3:$A$369)=TaxYear)*IFERROR('Trip Log'!$G$3:$G$369,0)) | E14: =SUMPRODUCT((MONTH('Trip Log'!$A$3:$A$369)=9)*(YEAR('Trip Log'!$A$3:$A$369)=TaxYear)*IFERROR('Trip Log'!$I$3:$I$369,0)) | F14: =SUMPRODUCT((MONTH('Trip Log'!$A$3:$A$369)=9)*(YEAR('Trip Log'!$A$3:$A$369)=TaxYear)*IFERROR('Trip Log'!$J$3:$J$369,0))
B15: October | C15: =SUMPRODUCT((MONTH('Trip Log'!$A$3:$A$369)=10)*(YEAR('Trip Log'!$A$3:$A$369)=TaxYear)*ISNUMBER('Trip Log'!$G$3:$G$369)) | D15: =SUMPRODUCT((MONTH('Trip Log'!$A$3:$A$369)=10)*(YEAR('Trip Log'!$A$3:$A$369)=TaxYear)*IFERROR('Trip Log'!$G$3:$G$369,0)) | E15: =SUMPRODUCT((MONTH('Trip Log'!$A$3:$A$369)=10)*(YEAR('Trip Log'!$A$3:$A$369)=TaxYear)*IFERROR('Trip Log'!$I$3:$I$369,0)) | F15: =SUMPRODUCT((MONTH('Trip Log'!$A$3:$A$369)=10)*(YEAR('Trip Log'!$A$3:$A$369)=TaxYear)*IFERROR('Trip Log'!$J$3:$J$369,0))
B16: November | C16: =SUMPRODUCT((MONTH('Trip Log'!$A$3:$A$369)=11)*(YEAR('Trip Log'!$A$3:$A$369)=TaxYear)*ISNUMBER('Trip Log'!$G$3:$G$369)) | D16: =SUMPRODUCT((MONTH('Trip Log'!$A$3:$A$369)=11)*(YEAR('Trip Log'!$A$3:$A$369)=TaxYear)*IFERROR('Trip Log'!$G$3:$G$369,0)) | E16: =SUMPRODUCT((MONTH('Trip Log'!$A$3:$A$369)=11)*(YEAR('Trip Log'!$A$3:$A$369)=TaxYear)*IFERROR('Trip Log'!$I$3:$I$369,0)) | F16: =SUMPRODUCT((MONTH('Trip Log'!$A$3:$A$369)=11)*(YEAR('Trip Log'!$A$3:$A$369)=TaxYear)*IFERROR('Trip Log'!$J$3:$J$369,0))
B17: December | C17: =SUMPRODUCT((MONTH('Trip Log'!$A$3:$A$369)=12)*(YEAR('Trip Log'!$A$3:$A$369)=TaxYear)*ISNUMBER('Trip Log'!$G$3:$G$369)) | D17: =SUMPRODUCT((MONTH('Trip Log'!$A$3:$A$369)=12)*(YEAR('Trip Log'!$A$3:$A$369)=TaxYear)*IFERROR('Trip Log'!$G$3:$G$369,0)) | E17: =SUMPRODUCT((MONTH('Trip Log'!$A$3:$A$369)=12)*(YEAR('Trip Log'!$A$3:$A$369)=TaxYear)*IFERROR('Trip Log'!$I$3:$I$369,0)) | F17: =SUMPRODUCT((MONTH('Trip Log'!$A$3:$A$369)=12)*(YEAR('Trip Log'!$A$3:$A$369)=TaxYear)*IFERROR('Trip Log'!$J$3:$J$369,0))
B18: Total | C18: =SUM(C6:C17) | D18: =SUM(D6:D17) | E18: =SUM(E6:E17) | F18: =SUM(F6:F17)
B21: By platform (full year)
B22: Platform | C22: Trips | D22: Business miles | E22: Deduction $
B23: =IFERROR(Setup!B19,"") | C23: =IF(B23="","",SUMPRODUCT(('Trip Log'!$C$3:$C$369=B23)*(YEAR('Trip Log'!$A$3:$A$369)=TaxYear)*ISNUMBER('Trip Log'!$G$3:$G$369))) | D23: =IF(B23="","",SUMPRODUCT(('Trip Log'!$C$3:$C$369=B23)*(YEAR('Trip Log'!$A$3:$A$369)=TaxYear)*IFERROR('Trip Log'!$I$3:$I$369,0))) | E23: =IF(B23="","",SUMPRODUCT(('Trip Log'!$C$3:$C$369=B23)*(YEAR('Trip Log'!$A$3:$A$369)=TaxYear)*IFERROR('Trip Log'!$J$3:$J$369,0)))
B24: =IFERROR(Setup!B20,"") | C24: =IF(B24="","",SUMPRODUCT(('Trip Log'!$C$3:$C$369=B24)*(YEAR('Trip Log'!$A$3:$A$369)=TaxYear)*ISNUMBER('Trip Log'!$G$3:$G$369))) | D24: =IF(B24="","",SUMPRODUCT(('Trip Log'!$C$3:$C$369=B24)*(YEAR('Trip Log'!$A$3:$A$369)=TaxYear)*IFERROR('Trip Log'!$I$3:$I$369,0))) | E24: =IF(B24="","",SUMPRODUCT(('Trip Log'!$C$3:$C$369=B24)*(YEAR('Trip Log'!$A$3:$A$369)=TaxYear)*IFERROR('Trip Log'!$J$3:$J$369,0)))
B25: =IFERROR(Setup!B21,"") | C25: =IF(B25="","",SUMPRODUCT(('Trip Log'!$C$3:$C$369=B25)*(YEAR('Trip Log'!$A$3:$A$369)=TaxYear)*ISNUMBER('Trip Log'!$G$3:$G$369))) | D25: =IF(B25="","",SUMPRODUCT(('Trip Log'!$C$3:$C$369=B25)*(YEAR('Trip Log'!$A$3:$A$369)=TaxYear)*IFERROR('Trip Log'!$I$3:$I$369,0))) | E25: =IF(B25="","",SUMPRODUCT(('Trip Log'!$C$3:$C$369=B25)*(YEAR('Trip Log'!$A$3:$A$369)=TaxYear)*IFERROR('Trip Log'!$J$3:$J$369,0)))
B26: =IFERROR(Setup!B22,"") | C26: =IF(B26="","",SUMPRODUCT(('Trip Log'!$C$3:$C$369=B26)*(YEAR('Trip Log'!$A$3:$A$369)=TaxYear)*ISNUMBER('Trip Log'!$G$3:$G$369))) | D26: =IF(B26="","",SUMPRODUCT(('Trip Log'!$C$3:$C$369=B26)*(YEAR('Trip Log'!$A$3:$A$369)=TaxYear)*IFERROR('Trip Log'!$I$3:$I$369,0))) | E26: =IF(B26="","",SUMPRODUCT(('Trip Log'!$C$3:$C$369=B26)*(YEAR('Trip Log'!$A$3:$A$369)=TaxYear)*IFERROR('Trip Log'!$J$3:$J$369,0)))
B27: =IFERROR(Setup!B23,"") | C27: =IF(B27="","",SUMPRODUCT(('Trip Log'!$C$3:$C$369=B27)*(YEAR('Trip Log'!$A$3:$A$369)=TaxYear)*ISNUMBER('Trip Log'!$G$3:$G$369))) | D27: =IF(B27="","",SUMPRODUCT(('Trip Log'!$C$3:$C$369=B27)*(YEAR('Trip Log'!$A$3:$A$369)=TaxYear)*IFERROR('Trip Log'!$I$3:$I$369,0))) | E27: =IF(B27="","",SUMPRODUCT(('Trip Log'!$C$3:$C$369=B27)*(YEAR('Trip Log'!$A$3:$A$369)=TaxYear)*IFERROR('Trip Log'!$J$3:$J$369,0)))
B28: =IFERROR(Setup!B24,"") | C28: =IF(B28="","",SUMPRODUCT(('Trip Log'!$C$3:$C$369=B28)*(YEAR('Trip Log'!$A$3:$A$369)=TaxYear)*ISNUMBER('Trip Log'!$G$3:$G$369))) | D28: =IF(B28="","",SUMPRODUCT(('Trip Log'!$C$3:$C$369=B28)*(YEAR('Trip Log'!$A$3:$A$369)=TaxYear)*IFERROR('Trip Log'!$I$3:$I$369,0))) | E28: =IF(B28="","",SUMPRODUCT(('Trip Log'!$C$3:$C$369=B28)*(YEAR('Trip Log'!$A$3:$A$369)=TaxYear)*IFERROR('Trip Log'!$J$3:$J$369,0)))
B29: =IFERROR(Setup!B25,"") | C29: =IF(B29="","",SUMPRODUCT(('Trip Log'!$C$3:$C$369=B29)*(YEAR('Trip Log'!$A$3:$A$369)=TaxYear)*ISNUMBER('Trip Log'!$G$3:$G$369))) | D29: =IF(B29="","",SUMPRODUCT(('Trip Log'!$C$3:$C$369=B29)*(YEAR('Trip Log'!$A$3:$A$369)=TaxYear)*IFERROR('Trip Log'!$I$3:$I$369,0))) | E29: =IF(B29="","",SUMPRODUCT(('Trip Log'!$C$3:$C$369=B29)*(YEAR('Trip Log'!$A$3:$A$369)=TaxYear)*IFERROR('Trip Log'!$J$3:$J$369,0)))
B30: =IFERROR(Setup!B26,"") | C30: =IF(B30="","",SUMPRODUCT(('Trip Log'!$C$3:$C$369=B30)*(YEAR('Trip Log'!$A$3:$A$369)=TaxYear)*ISNUMBER('Trip Log'!$G$3:$G$369))) | D30: =IF(B30="","",SUMPRODUCT(('Trip Log'!$C$3:$C$369=B30)*(YEAR('Trip Log'!$A$3:$A$369)=TaxYear)*IFERROR('Trip Log'!$I$3:$I$369,0))) | E30: =IF(B30="","",SUMPRODUCT(('Trip Log'!$C$3:$C$369=B30)*(YEAR('Trip Log'!$A$3:$A$369)=TaxYear)*IFERROR('Trip Log'!$J$3:$J$369,0)))
B31: =IFERROR(Setup!B27,"") | C31: =IF(B31="","",SUMPRODUCT(('Trip Log'!$C$3:$C$369=B31)*(YEAR('Trip Log'!$A$3:$A$369)=TaxYear)*ISNUMBER('Trip Log'!$G$3:$G$369))) | D31: =IF(B31="","",SUMPRODUCT(('Trip Log'!$C$3:$C$369=B31)*(YEAR('Trip Log'!$A$3:$A$369)=TaxYear)*IFERROR('Trip Log'!$I$3:$I$369,0))) | E31: =IF(B31="","",SUMPRODUCT(('Trip Log'!$C$3:$C$369=B31)*(YEAR('Trip Log'!$A$3:$A$369)=TaxYear)*IFERROR('Trip Log'!$J$3:$J$369,0)))
B32: =IFERROR(Setup!B28,"") | C32: =IF(B32="","",SUMPRODUCT(('Trip Log'!$C$3:$C$369=B32)*(YEAR('Trip Log'!$A$3:$A$369)=TaxYear)*ISNUMBER('Trip Log'!$G$3:$G$369))) | D32: =IF(B32="","",SUMPRODUCT(('Trip Log'!$C$3:$C$369=B32)*(YEAR('Trip Log'!$A$3:$A$369)=TaxYear)*IFERROR('Trip Log'!$I$3:$I$369,0))) | E32: =IF(B32="","",SUMPRODUCT(('Trip Log'!$C$3:$C$369=B32)*(YEAR('Trip Log'!$A$3:$A$369)=TaxYear)*IFERROR('Trip Log'!$J$3:$J$369,0)))
B33: =IFERROR(Setup!B29,"") | C33: =IF(B33="","",SUMPRODUCT(('Trip Log'!$C$3:$C$369=B33)*(YEAR('Trip Log'!$A$3:$A$369)=TaxYear)*ISNUMBER('Trip Log'!$G$3:$G$369))) | D33: =IF(B33="","",SUMPRODUCT(('Trip Log'!$C$3:$C$369=B33)*(YEAR('Trip Log'!$A$3:$A$369)=TaxYear)*IFERROR('Trip Log'!$I$3:$I$369,0))) | E33: =IF(B33="","",SUMPRODUCT(('Trip Log'!$C$3:$C$369=B33)*(YEAR('Trip Log'!$A$3:$A$369)=TaxYear)*IFERROR('Trip Log'!$J$3:$J$369,0)))
B34: =IFERROR(Setup!B30,"") | C34: =IF(B34="","",SUMPRODUCT(('Trip Log'!$C$3:$C$369=B34)*(YEAR('Trip Log'!$A$3:$A$369)=TaxYear)*ISNUMBER('Trip Log'!$G$3:$G$369))) | D34: =IF(B34="","",SUMPRODUCT(('Trip Log'!$C$3:$C$369=B34)*(YEAR('Trip Log'!$A$3:$A$369)=TaxYear)*IFERROR('Trip Log'!$I$3:$I$369,0))) | E34: =IF(B34="","",SUMPRODUCT(('Trip Log'!$C$3:$C$369=B34)*(YEAR('Trip Log'!$A$3:$A$369)=TaxYear)*IFERROR('Trip Log'!$J$3:$J$369,0)))

Sheet Year-End Summary
B2: Year-End Summary
B3: What to put on Schedule C line 9 (Car & Truck Expenses) when you file.
B5: TAX YEAR | C5: TOTAL BUSINESS MILES | D5: IRS RATE | E5: MILEAGE DEDUCTION
B6: =TaxYear | C6: ='Monthly Summary'!E18 | D6: =MileRate | E6: ='Monthly Summary'!F18
B10: Schedule C — Part II, Line 9 (Car & Truck Expenses):
B11: ="Enter $"&TEXT('Monthly Summary'!F18,"#,##0.00")&" on line 9. Use the 'Standard Mileage' method (the option you've been tracking for)."
B14: Sanity check vs. your total driving
B15: Total miles all vehicles drove this year (from Setup): | C15: =SUM(Setup!F12:F14)
B16: Business miles you logged this year: | C16: ='Monthly Summary'!E18
B17: Implied business-use percentage: | C17: =IFERROR(C16/C15,"")
B18: If this percentage is above ~85%, expect IRS questions — most gig drivers fall in the 50–85% range because of commute, personal errands, and time between gigs. Reasonable numbers help you survive an audit.
B21: Records to keep with this file (3+ years)
B22: → | C22: Jan 1 and Dec 31 odometer photos for every vehicle you used
B23: → | C23: 1099-NEC and 1099-K from every platform
B24: → | C24: Bank/PayPal statements showing platform deposits
B25: → | C25: Receipts for tolls, parking, and any non-mileage car costs (these add on top of the mileage deduction)
B26: → | C26: If you ever switched from standard mileage to actual expenses, keep that election documented

Sheet IRS Reference
B2: Plain-English IRS Reference
B3: What every gig driver needs to know — short answers to the questions the IRS actually cares about.
B5: Q | C5: Standard mileage vs. actual expenses
C6: You pick one method per vehicle. Standard mileage (this tracker) multiplies your business miles by the IRS rate — no receipts needed beyond the log. Actual expenses adds up gas, oil, repairs, insurance, depreciation, etc., then multiplies by business-use %. Most gig drivers come out ahead with standard mileage and it's way less paperwork.
B8: Q | C8: Can I switch methods later?
C9: If you used STANDARD mileage in year one, you can switch to actual in any later year. If you used ACTUAL in year one, you're locked into actual for that vehicle for as long as you own it. This is why year-one choice matters.
B11: Q | C11: What counts as a business mile?
C12: Driving with the app on and waiting for/accepting/completing rides or deliveries. Driving from one delivery to the next while online. Driving home after your shift IS a business mile if you're online and accepting requests. Plain personal errands are not.
B14: Q | C14: Is my commute deductible?
C15: Your drive from home to your first business pickup is generally NOT deductible (commuting). Once you're logged into the app and accepting work, you've started your business — miles from that point until you log off ARE deductible. Some drivers turn the app on as they leave the driveway specifically for this reason.
B17: Q | C17: Do tolls and parking count?
C18: Yes, on top of the mileage deduction. Track them separately and add them to Schedule C — they don't go in this tracker because they aren't mileage.
B20: Q | C20: What about my phone, car wash, and hot bag?
C21: Phone (business-use %), car washes, delivery bags, accessories, and required gear go on Schedule C as separate expenses — not in this tracker. The mileage deduction only covers what the IRS calls the operating cost of the vehicle.
B23: Q | C23: How long do I keep this log?
C24: At least 3 years after you file. The IRS can audit up to 3 years routinely, 6 years for substantial under-reporting, and indefinitely for fraud. Save a PDF export each year and stash it with your tax records.
B26: Q | C26: What if I drove for two platforms at the same time?
C27: Log it once. You can't double-count miles. Pick the platform you were primarily working for on that trip.
B29: Q | C29: Do I need a paper log too?
C30: No. The IRS accepts digital records as long as they're contemporaneous (entered close to when the trip happened) and complete. This spreadsheet meets that standard.
B32: Q | C32: What if I forget to log a day?
C33: Reconstruct it from your platform's trip history (DoorDash, Uber, Lyft, etc. all keep one) within a few days. The IRS calls this 'reasonable reconstruction.' Don't wait until April.
