Workbook
Name TaxYear: Setup!$C$6
Name FilingStatus: Setup!$C$7
Name StateCode: Setup!$C$8
Name StateRate: Setup!$C$9
Name SEOverride: Setup!$C$12
Name W2Income: Setup!$C$13
Name W2Withheld: Setup!$C$14
Name LastYearTax: Setup!$C$17
Name LastYearAGI: Setup!$C$18
Name StdDedSingle: Setup!$C$21
Name StdDedMFJ: Setup!$C$22
Name StdDedHOH: Setup!$C$23
Name SSWageBase: Setup!$C$24
Name BracketsSingle: Setup!$B$28:$B$34
Name BracketsMFJ: Setup!$C$28:$C$34
Name BracketsRate: Setup!$D$28:$D$34
Name Q1Income: 'Income Forecast'!$D$22
Name Q2Income: 'Income Forecast'!$D$23
Name Q3Income: 'Income Forecast'!$D$24
Name Q4Income: 'Income Forecast'!$D$25
Name AnnualSEForecast: 'Income Forecast'!$I$18
Name NetFedOwed: 'Tax Calculator'!$C$23
Name NetStateOwed: 'Tax Calculator'!$C$24
Name TotalFedTax: 'Tax Calculator'!$C$21
Name SETax: 'Tax Calculator'!$C$10
Name FedIncomeTax: 'Tax Calculator'!$C$17
Name FedPaidYTD: 'Quarterly Payments'!$F$11
Name StatePaidYTD: 'Quarterly Payments'!$F$20

Sheet Start Here
B2: Quarterly Tax System 2026
B3: SideHustleGuard · sidehustleguard.com
B6: What this tool does
B7: Tells you exactly how much to send the IRS (and your state) each quarter so you never get hit with an underpayment penalty in April. Works for any self-employed income — gig driving, Airbnb, Etsy, freelance, consulting, multiple streams. Builds a complete record of every payment so when you sit down with your CPA in March, the work is already done.
B9: How to use it (3 steps)
B10: 1. | C10: Fill in the Setup tab. | D10: Filing status, state, what you expect to make this year, what you owed in tax last year, and any W-2 income from a day job. Defaults are pre-filled — just edit the gold cells.
B11: 2. | C11: Forecast your year on the Income Forecast tab. | D11: Drop in your expected net income (after deductions like mileage) for each month. You can break it down by platform (DoorDash + Etsy + freelance) or just enter one annual number.
B12: 3. | C12: Check the Quarterly Payments tab before each due date. | D12: It shows you exactly what to send the IRS for Q1, Q2, Q3, Q4, and the state. Log each payment in the same tab so you have a complete record.
B14: Quarterly due dates
B15: Quarter | C15: Covers income from | D15: Federal due | F15: State due (most states)
B16: Q1 | C16: Jan – Mar | D16: April 15 | F16: April 15 (same)
B17: Q2 | C17: Apr – May | D17: June 15 | F17: June 15 (same)
B18: Q3 | C18: Jun – Aug | D18: September 15 | F18: September 15 (same)
B19: Q4 | C19: Sep – Dec | D19: January 15 (next year) | F19: January 15 (next year)
B21: Why this matters
B22: If you owe more than $1,000 in tax and didn't make quarterly payments — or paid less than the "safe harbor" amount — the IRS adds an underpayment penalty on top of what you owe. The penalty is calculated quarterly at the federal short-term rate plus 3% (typically 6–8% annualized). On a $15,000 tax bill, that's an extra $400–$800 that didn't have to exist. This tool exists to make sure you hit one of the two safe-harbor tests so the penalty never applies.
B24: Educational tool only — not tax or legal advice. Tax brackets, SE tax wage base, and state rates change annually. Verify all defaults against current IRS and state publications. For complex situations (W-2 + SE income, joint filers with separate businesses, large investment income), consult a CPA.

Sheet Setup
B2: Setup
B3: Edit the gold cells. Everything else reads from here.
B5: Year & filing status
B6: Tax year | C6: 2026 | D6: The year you're paying taxes for
B7: Filing status | C7: Single | D7: Single, MFJ, MFS, HOH
B8: State | C8: CA | D8: Two-letter code (e.g., CA, TX, FL, NY)
B9: State flat estimated tax rate | C9: 0.06 | D9: Override the lookup below if you know your effective rate. Edit at any time.
B11: This year's income (overrides if filled)
B12: Estimated net self-employment income (annual) | C12: 0 | D12: Leave 0 to use the month-by-month forecast on the Income Forecast tab
B13: W-2 income (if you also have a day job) | C13: 0 | D13: Gross wages, before tax
B14: Federal tax withheld from W-2 (this year) | C14: 0 | D14: From your most recent paystub × pay periods left, or your W-2 box 2
B16: Last year — for safe harbor calculation
B17: Total federal tax owed last year (Form 1040 line 24) | C17: 0 | D17: Look at last year's return. This sets the 100%/110% safe harbor.
B18: Last year's AGI (Form 1040 line 11) | C18: 0 | D18: If above $150K, safe harbor is 110% of last year's tax instead of 100%
B20: Federal tax constants (edit each year)
B21: Standard deduction (single / MFS) | C21: 15750 | D21: 2025 value as published by IRS. Update for your tax year.
B22: Standard deduction (MFJ) | C22: 31500 | D22: 2025 value
B23: Standard deduction (HOH) | C23: 23625 | D23: 2025 value
B24: Social Security wage base | C24: 176100 | D24: 2025 value. SE tax SS portion (12.4%) only applies up to this.
B26: Federal income tax brackets (2025 — edit each year)
B27: Bracket top (Single) | C27: Bracket top (MFJ) | D27: Marginal rate
B28: 11925 | C28: 23850 | D28: 0.1
B29: 48475 | C29: 96950 | D29: 0.12
B30: 103350 | C30: 206700 | D30: 0.22
B31: 197300 | C31: 394600 | D31: 0.24
B32: 250525 | C32: 501050 | D32: 0.32
B33: 626350 | C33: 751600 | D33: 0.35
B34: 999999999 | C34: 999999999 | D34: 0.37
B36: HoH and MFS brackets aren't modeled separately — if you use those statuses, set filing status above to the closest match (HOH → MFJ for brackets, MFS → Single) and adjust the standard deduction. For complex returns, consult a CPA.

Sheet Income Forecast
B2: Income Forecast
B3: Net self-employment income per month (gross minus deductions like mileage). Add platforms in row 5 — up to 6 streams.
B4: Hint: if you'd rather just enter one annual number, fill in "Estimated net SE income (annual)" on the Setup tab — that will override this forecast.
B5: Month | C5: DoorDash | D5: Uber / Lyft | E5: Airbnb / STR | F5: Etsy / sales | G5: Freelance | H5: Other | I5: Total
B6: January | C6: 0 | D6: 0 | E6: 0 | F6: 0 | G6: 0 | H6: 0 | I6: =SUM(C6:H6)
B7: February | C7: 0 | D7: 0 | E7: 0 | F7: 0 | G7: 0 | H7: 0 | I7: =SUM(C7:H7)
B8: March | C8: 0 | D8: 0 | E8: 0 | F8: 0 | G8: 0 | H8: 0 | I8: =SUM(C8:H8)
B9: April | C9: 0 | D9: 0 | E9: 0 | F9: 0 | G9: 0 | H9: 0 | I9: =SUM(C9:H9)
B10: May | C10: 0 | D10: 0 | E10: 0 | F10: 0 | G10: 0 | H10: 0 | I10: =SUM(C10:H10)
B11: June | C11: 0 | D11: 0 | E11: 0 | F11: 0 | G11: 0 | H11: 0 | I11: =SUM(C11:H11)
B12: July | C12: 0 | D12: 0 | E12: 0 | F12: 0 | G12: 0 | H12: 0 | I12: =SUM(C12:H12)
B13: August | C13: 0 | D13: 0 | E13: 0 | F13: 0 | G13: 0 | H13: 0 | I13: =SUM(C13:H13)
B14: September | C14: 0 | D14: 0 | E14: 0 | F14: 0 | G14: 0 | H14: 0 | I14: =SUM(C14:H14)
B15: October | C15: 0 | D15: 0 | E15: 0 | F15: 0 | G15: 0 | H15: 0 | I15: =SUM(C15:H15)
B16: November | C16: 0 | D16: 0 | E16: 0 | F16: 0 | G16: 0 | H16: 0 | I16: =SUM(C16:H16)
B17: December | C17: 0 | D17: 0 | E17: 0 | F17: 0 | G17: 0 | H17: 0 | I17: =SUM(C17:H17)
B18: Annual total | C18: =SUM(C6:C17) | D18: =SUM(D6:D17) | E18: =SUM(E6:E17) | F18: =SUM(F6:F17) | G18: =SUM(G6:G17) | H18: =SUM(H6:H17) | I18: =SUM(I6:I17)
B20: By quarter
B21: Quarter | C21: Months | D21: Net SE income
B22: Q1 | C22: Jan–Mar | D22: =SUM(I6:I8)
B23: Q2 | C23: Apr–May | D23: =SUM(I9:I10)
B24: Q3 | C24: Jun–Aug | D24: =SUM(I11:I13)
B25: Q4 | C25: Sep–Dec | D25: =SUM(I14:I17)

Sheet Tax Calculator
B2: Tax Calculator
B3: All numbers below are calculated — don't edit. To change inputs, use the Setup tab.
B5: Self-employment income & SE tax
B6: Net SE income (this year) | C6: =IF(SEOverride>0,SEOverride,AnnualSEForecast) | D6: From Setup override if filled; otherwise the Income Forecast annual total
B7: × 92.35% (SE tax base) | C7: ='Tax Calculator'!$C$6*0.9235 | D7: The IRS taxes 92.35% of SE income for Social Security & Medicare
B8: Social Security portion of SE tax (12.4% up to wage base) | C8: =MIN('Tax Calculator'!$C$7,SSWageBase)*0.124 | D8: Stops at the SS wage base (set on Setup tab)
B9: Medicare portion of SE tax (2.9%) | C9: ='Tax Calculator'!$C$7*0.029 | D9: No income cap on Medicare
B10: Total SE tax | C10: ='Tax Calculator'!$C$8+'Tax Calculator'!$C$9 | D10: Sum of Social Security + Medicare
B11: Deductible half of SE tax | C11: ='Tax Calculator'!$C$10/2 | D11: Half of SE tax reduces your AGI (it's an above-the-line deduction)
B13: Federal income tax
B14: AGI (W-2 + net SE − half SE tax) | C14: =W2Income+'Tax Calculator'!$C$6-'Tax Calculator'!$C$11 | D14: Adjusted Gross Income — the number tax brackets apply to (after standard deduction)
B15: Standard deduction (based on filing status) | C15: =IF(FilingStatus="MFJ",StdDedMFJ,IF(FilingStatus="HOH",StdDedHOH,StdDedSingle)) | D15: Auto-picks the right standard deduction; MFS uses Single
B16: Taxable income | C16: =MAX('Tax Calculator'!$C$14-'Tax Calculator'!$C$15,0) | D16: AGI minus standard deduction (we don't model QBI or itemized — see CPA if relevant)
B17: Federal income tax (bracket calc) | C17: =IF(FilingStatus="MFJ",SUMPRODUCT(((MIN('Tax Calculator'!$C$16,BracketsMFJ)-IFERROR(OFFSET(BracketsMFJ,-1,0),0))>0)*(MIN('Tax Calculator'!$C$16,BracketsMFJ)-IFERROR(OFFSET(BracketsMFJ,-1,0),0))*BracketsRate),SUMPRODUCT(((MIN('Tax Calculator'!$C$16,BracketsSingle)-IFERROR(OFFSET(BracketsSingle,-1,0),0))>0)*(MIN('Tax Calculator'!$C$16,BracketsSingle)-IFERROR(OFFSET(BracketsSingle,-1,0),0))*BracketsRate)) | D17: Applied bracket-by-bracket to your taxable income
B19: State tax & totals
B20: State income tax (flat rate × taxable income) | C20: ='Tax Calculator'!$C$16*StateRate | D20: Rough estimate — actual state tax varies by bracket. Override the rate on Setup if you have a better number.
B21: Total federal owed (SE + income) | C21: ='Tax Calculator'!$C$10+'Tax Calculator'!$C$17 | D21: What you owe the IRS this year, before W-2 withholding
B22: Less: W-2 federal withholding | C22: =-W2Withheld | D22: Subtracts what your employer already sent in for you
B23: =Net federal owed (quarterly target) | C23: ='Tax Calculator'!$C$21-W2Withheld | D23: Divide this by 4 to get your quarterly federal payment
B24: Total state owed (quarterly target) | C24: ='Tax Calculator'!$C$20 | D24: Divide this by 4 to get your quarterly state payment

Sheet Quarterly Payments
B2: Quarterly Payments
B3: Log each payment after you make it. Status colors track whether you're on pace to hit your annual target.
B5: Federal (IRS)
B6: Q | C6: Due date | D6: Target $ | E6: Paid date | F6: Paid $ | G6: Method | H6: Status
B7: Q1 | C7: April 15 | D7: =NetFedOwed/4 | H7: =IF(F7="","Not paid yet",IF(F7>=D7*0.95,"On track","Underpaid by $"&TEXT(D7-F7,"#,##0")))
B8: Q2 | C8: June 15 | D8: =NetFedOwed/4 | H8: =IF(F8="","Not paid yet",IF(F8>=D8*0.95,"On track","Underpaid by $"&TEXT(D8-F8,"#,##0")))
B9: Q3 | C9: September 15 | D9: =NetFedOwed/4 | H9: =IF(F9="","Not paid yet",IF(F9>=D9*0.95,"On track","Underpaid by $"&TEXT(D9-F9,"#,##0")))
B10: Q4 | C10: January 15 | D10: =NetFedOwed/4 | H10: =IF(F10="","Not paid yet",IF(F10>=D10*0.95,"On track","Underpaid by $"&TEXT(D10-F10,"#,##0")))
B11: Total | D11: =SUM(D7:D10) | F11: =SUM(F7:F10) | H11: =IF(F11>=D11*0.95,"Annual target met","Short $"&TEXT(D11-F11,"#,##0"))
B14: State
B15: Q | C15: Due date | D15: Target $ | E15: Paid date | F15: Paid $ | G15: Method | H15: Status
B16: Q1 | C16: April 15 | D16: =NetStateOwed/4 | H16: =IF(F16="","Not paid yet",IF(F16>=D16*0.95,"On track","Underpaid by $"&TEXT(D16-F16,"#,##0")))
B17: Q2 | C17: June 15 | D17: =NetStateOwed/4 | H17: =IF(F17="","Not paid yet",IF(F17>=D17*0.95,"On track","Underpaid by $"&TEXT(D17-F17,"#,##0")))
B18: Q3 | C18: September 15 | D18: =NetStateOwed/4 | H18: =IF(F18="","Not paid yet",IF(F18>=D18*0.95,"On track","Underpaid by $"&TEXT(D18-F18,"#,##0")))
B19: Q4 | C19: January 15 | D19: =NetStateOwed/4 | H19: =IF(F19="","Not paid yet",IF(F19>=D19*0.95,"On track","Underpaid by $"&TEXT(D19-F19,"#,##0")))
B20: Total | D20: =SUM(D16:D19) | F20: =SUM(F16:F19)

Sheet Safe Harbor
B2: Safe Harbor Check
B3: The IRS won't charge you an underpayment penalty if you hit EITHER of these two safe-harbor tests. You only need ONE.
B5: Safe Harbor 1 — based on last year's tax
B6: Required multiplier (110% if last year AGI > $150K, else 100%) | C6: =IF(LastYearAGI>150000,1.1,1) | D6: The 110% rule kicks in for higher earners
B7: Safe harbor target (last year's tax × multiplier) | C7: =LastYearTax*C6 | D7: If you pay AT LEAST this much across all 4 quarters + W-2 withholding, you're safe
B8: Paid so far (Q1–Q4 federal + W-2 withholding) | C8: =FedPaidYTD+W2Withheld | D8: From Quarterly Payments tab + W-2 withholding on Setup
B9: Safe Harbor 1 status: | C9: =IF(C8>=C7,"✓ SAFE","Short $"&TEXT(C7-C8,"#,##0"))
B11: Safe Harbor 2 — based on this year's tax
B12: This year's projected total federal tax | C12: =TotalFedTax | D12: From Tax Calculator
B13: Safe harbor target (90% of this year's tax) | C13: =C12*0.9 | D13: If you pay at least 90% of what you'll actually owe, you're safe
B14: Paid so far (Q1–Q4 federal + W-2 withholding) | C14: =FedPaidYTD+W2Withheld | D14: Same total as Safe Harbor 1
B15: Safe Harbor 2 status: | C15: =IF(C14>=C13,"✓ SAFE","Short $"&TEXT(C13-C14,"#,##0"))
B17: Are you penalty-safe?
B18: Overall status: | C18: =IF(OR(C8>=C7,C14>=C13),"✓ YES — you're safe from penalty","⚠ Not yet — close one of the gaps above")
B20: You only need to satisfy ONE of the two tests to avoid the underpayment penalty. Most side hustlers hit Safe Harbor 1 because it's easier — you just need to pay last year's tax bill across four equal quarters. Safe Harbor 2 is for years when your income drops significantly.

Sheet IRS Reference
B2: IRS & State Quarterly Tax Reference
B3: Plain-English answers to what gets people in trouble.
B5: Q | C5: Where do I actually pay federal quarterly tax?
C6: Three options. (1) IRS Direct Pay — irs.gov/payments/direct-pay — free, takes 2 minutes, pulls from a bank account. (2) EFTPS — eftps.gov — also free, requires a one-time enrollment, better if you want a permanent payment history. (3) Mail a check with Form 1040-ES voucher to the IRS address listed on the form for your state. Direct Pay is the easiest for almost everyone.
B8: Q | C8: Do I need to file Form 1040-ES?
C9: Technically no — Form 1040-ES is the paper voucher you mail with a check. If you pay electronically via Direct Pay or EFTPS, you don't file anything; the payment IS the filing. Just keep your confirmation number with your tax records.
B11: Q | C11: How does the state work?
C12: Every state with income tax has its own quarterly system. Most (CA, NY, IL, etc.) mirror the federal due dates. Search "[your state] estimated tax payments" — usually it's a one-page payment portal on your state's revenue/tax department site. California is FTB Web Pay. New York is the IT-2105 voucher or online via NY.gov. Texas, Florida, Washington, Nevada, Tennessee, South Dakota, Wyoming, Alaska, and New Hampshire have no state income tax — skip this entirely.
B14: Q | C14: What if my income is uneven across the year?
C15: You can use the "annualized income installment method" (Form 2210, Schedule AI) to pay less in slow quarters and more in busy ones — but it's a pain. Most people just pay equal quarters using Safe Harbor 1 (100% / 110% of last year's tax), which doesn't care when the income actually comes in.
B17: Q | C17: What's the actual penalty if I skip a quarter?
C18: The IRS charges the federal short-term rate + 3% on the underpaid amount, calculated quarterly. In 2025 that worked out to ~8% annualized. So if you should have paid $3,000 for Q1 and didn't, by April you owe an extra ~$60. Skip all four quarters on a $15K bill and you're looking at $400-$800 in penalties. The penalty is non-deductible — pure waste.
B20: Q | C20: Can I overpay to be safe?
C21: Yes, and many people do. Pay an extra 5-10% per quarter to give yourself buffer; the IRS refunds the excess (or rolls it forward) when you file. There's no penalty for overpaying. The only "cost" is the lost interest on that cash — usually pennies compared to the underpayment penalty.
B23: Q | C23: I had a huge year. Last year was tiny. Do I really only owe what last year's tax was × 4?
C24: Under Safe Harbor 1, yes — for THIS year. You hit the safe harbor by paying 100%/110% of last year's tax. The catch: in April when you file, you'll owe a LARGE balance for this year's true tax. No penalty, but the bill is still due. Start putting cash aside in a separate account so April doesn't bury you.
B26: Q | C26: What if I miss a quarter and want to catch up?
C27: Pay the missed amount as soon as you can with your next payment. The penalty accrues per day, so paying late is much better than not paying. You can't "backdate" a quarter, but you can stop the bleeding.
B29: Q | C29: Does this work if I'm both W-2 and self-employed?
C30: Yes. The Tax Calculator already factors in your W-2 income and withholding. The Net federal owed number on that tab assumes your employer's withholding takes care of the W-2 portion, so you only need to send quarterlies for the SE side. Make sure the W-2 withholding number you entered is the FULL YEAR amount, not just YTD.
B32: Q | C32: Do I need to keep records of payments?
C33: Yes — keep electronic confirmations (Direct Pay sends an email; EFTPS keeps history online; mailed checks → keep the bank's cleared-check image). Match these to the Paid date and Paid $ columns on the Quarterly Payments tab. At year-end, the total of your four quarterly payments goes on Form 1040 line 26.
